raytf/__init__.py
raytf/gang_scheduler.py
raytf/log_utils.py
raytf/raytf_driver.py
raytf/raytf_executor.py
raytf/runtime.py
raytf/tf_cluster_driver.py
raytf/tf_executor.py
raytf/tf_runtime.py
raytf/tool_utils.py
raytf-0.0.1.dist-info/METADATA
raytf-0.0.1.dist-info/WHEEL
raytf-0.0.1.dist-info/top_level.txt
raytf-0.0.1.dist-info/RECORD
