Metadata-Version: 2.1
Name: raytf
Version: 0.0.1
Summary: Tensorflow Cluster on Ray
Home-page: https://github.com/zuston/raytf
Author: junfan.zhang
Author-email: junfan.zhang@outlook.com
License: BSD License
Platform: all
Classifier: Intended Audience :: Developers
Classifier: Operating System :: OS Independent
Classifier: Natural Language :: Chinese (Simplified)
Classifier: Programming Language :: Python :: 3
Classifier: Programming Language :: Python :: 3.5
Classifier: Programming Language :: Python :: 3.6
Classifier: Programming Language :: Python :: 3.7
Classifier: Programming Language :: Python :: 3.8
Classifier: Topic :: Software Development :: Libraries
